kolla_ansible/__init__.py
kolla_ansible/version.py
kolla_ansible/cmd/__init__.py
kolla_ansible/cmd/genpwd.py
kolla_ansible/cmd/mergepwd.py
kolla_ansible-6.2.3.data/data/share/kolla-ansible/init-runonce
kolla_ansible-6.2.3.data/data/share/kolla-ansible/init-vpn
kolla_ansible-6.2.3.data/data/share/kolla-ansible/openrc-example
kolla_ansible-6.2.3.data/data/share/kolla-ansible/setup.cfg
kolla_ansible-6.2.3.data/data/share/kolla-ansible/ansible/bifrost.yml
kolla_ansible-6.2.3.data/data/share/kolla-ansible/ansible/certificates.yml
kolla_ansible-6.2.3.data/data/share/kolla-ansible/ansible/destroy.yml
kolla_ansible-6.2.3.data/data/share/kolla-ansible/ansible/gather-facts.yml
kolla_ansible-6.2.3.data/data/share/kolla-ansible/ansible/kolla-host.yml
kolla_ansible-6.2.3.data/data/share/kolla-ansible/ansible/mariadb_recovery.yml
kolla_ansible-6.2.3.data/data/share/kolla-ansible/ansible/post-deploy.yml
kolla_ansible-6.2.3.data/data/share/kolla-ansible/ansible/site.yml
kolla_ansible-6.2.3.data/data/share/kolla-ansible/ansible/stop.yml
kolla_ansible-6.2.3.data/data/share/kolla-ansible/ansible/action_plugins/merge_configs.py
kolla_ansible-6.2.3.data/data/share/kolla-ansible/ansible/action_plugins/merge_yaml.py
kolla_ansible-6.2.3.data/data/share/kolla-ansible/ansible/group_vars/all.yml
kolla_ansible-6.2.3.data/data/share/kolla-ansible/ansible/inventory/all-in-one
kolla_ansible-6.2.3.data/data/share/kolla-ansible/ansible/inventory/multinode
kolla_ansible-6.2.3.data/data/share/kolla-ansible/ansible/library/bslurp.py
kolla_ansible-6.2.3.data/data/share/kolla-ansible/ansible/library/kolla_ceph_keyring.py
kolla_ansible-6.2.3.data/data/share/kolla-ansible/ansible/library/kolla_container_facts.py
kolla_ansible-6.2.3.data/data/share/kolla-ansible/ansible/library/kolla_docker.py
kolla_ansible-6.2.3.data/data/share/kolla-ansible/ansible/library/kolla_toolbox.py
kolla_ansible-6.2.3.data/data/share/kolla-ansible/ansible/library/merge_configs.py
kolla_ansible-6.2.3.dist-info/AUTHORS
kolla_ansible-6.2.3.dist-info/LICENSE
kolla_ansible-6.2.3.dist-info/METADATA
kolla_ansible-6.2.3.dist-info/WHEEL
kolla_ansible-6.2.3.dist-info/entry_points.txt
kolla_ansible-6.2.3.dist-info/pbr.json
kolla_ansible-6.2.3.dist-info/top_level.txt
kolla_ansible-6.2.3.dist-info/RECORD
