Metadata-Version: 2.1
Name: kolla-ansible
Version: 6.2.3
Summary: Ansible Deployment of Kolla containers
Home-page: https://docs.openstack.org/kolla-ansible/latest/
Author: OpenStack
Author-email: openstack-dev@lists.openstack.org
License: Apache License, Version 2.0
Platform: UNKNOWN
Classifier: Environment :: OpenStack
Classifier: Intended Audience :: Information Technology
Classifier: Intended Audience :: System Administrators
Classifier: License :: OSI Approved :: Apache Software License
Classifier: Operating System :: POSIX :: Linux
Classifier: Programming Language :: Python
Classifier: Programming Language :: Python :: 2
Classifier: Programming Language :: Python :: 2.7
Classifier: Programming Language :: Python :: 3
Classifier: Programming Language :: Python :: 3.5
Requires-Dist: pbr (!=2.1.0,>=2.0.0)
Requires-Dist: docker (>=2.4.2)
Requires-Dist: Jinja2 (!=2.9.0,!=2.9.1,!=2.9.2,!=2.9.3,!=2.9.4,>=2.8)
Requires-Dist: six (>=1.10.0)
Requires-Dist: oslo.config (>=5.1.0)
Requires-Dist: oslo.utils (>=3.33.0)
Requires-Dist: setuptools (!=24.0.0,!=34.0.0,!=34.0.1,!=34.0.2,!=34.0.3,!=34.1.0,!=34.1.1,!=34.2.0,!=34.3.0,!=34.3.1,!=34.3.2,!=36.2.0,>=16.0)
Requires-Dist: PyYAML (>=3.10)
Requires-Dist: netaddr (>=0.7.18)
Requires-Dist: cryptography (!=2.0,>=1.9)
Requires-Dist: jmespath (>=0.9.0)
